varikn-1.2.1.dist-info/WHEEL
varikn-1.2.1.dist-info/top_level.txt
varikn-1.2.1.dist-info/RECORD
varikn-1.2.1.dist-info/METADATA
varikn/VariKNPYTHON_wrap.cxx
varikn/__init__.py
varikn/_varikn.so
varikn/_version.py
varikn/wrapper.py
