Metadata-Version: 2.1
Name: varikn
Version: 1.2.1
Summary: VariKN language modeling toolkit
Home-page: https://github.com/vsiivola/variKN
Author: Vesa Siivola
License: BSD 3-Clause License
